UnlimitedGPT/UnlimitedGPT.py
UnlimitedGPT/__init__.py
UnlimitedGPT/internal/driver.py
UnlimitedGPT/internal/exceptions.py
UnlimitedGPT/internal/objects.py
UnlimitedGPT/internal/selectors.py
UnlimitedGPT-0.1.9.3.dist-info/LICENSE
UnlimitedGPT-0.1.9.3.dist-info/METADATA
UnlimitedGPT-0.1.9.3.dist-info/WHEEL
UnlimitedGPT-0.1.9.3.dist-info/top_level.txt
UnlimitedGPT-0.1.9.3.dist-info/RECORD
